LICENSE
README.md
setup.py
kaiyo/__init__.py
kaiyo/kaiyo.py
kaiyo.egg-info/PKG-INFO
kaiyo.egg-info/SOURCES.txt
kaiyo.egg-info/dependency_links.txt
kaiyo.egg-info/entry_points.txt
kaiyo.egg-info/top_level.txt
kaiyo/modules/__init__.py
kaiyo/modules/kaiyoconsole.py
kaiyo/modules/kaiyosetup.py
kaiyo/utils/__init__.py
kaiyo/utils/clickUtils.py
kaiyo/utils/configUtil.py
kaiyo/utils/consoleUtil.py
kaiyo/utils/helpers.py
kaiyo/utils/restClient.py