Metadata-Version: 2.1
Name: kaiyo
Version: 0.0.0
Summary: Instant deployment
Author: Mayank Aggarwal
Author-email: support@kaiyo.dev
License: MIT
Classifier: License :: OSI Approved :: MIT License
Classifier: Programming Language :: Python :: 3
Classifier: Programming Language :: Python :: 3.7
License-File: LICENSE
